cdk_demo_construct/__init__.py
cdk_demo_construct/py.typed
cdk_demo_construct/_jsii/__init__.py
cdk_demo_construct/_jsii/cdk-demo-construct@0.0.186.jsii.tgz
cdk_demo_construct-0.0.186.dist-info/LICENSE
cdk_demo_construct-0.0.186.dist-info/METADATA
cdk_demo_construct-0.0.186.dist-info/WHEEL
cdk_demo_construct-0.0.186.dist-info/top_level.txt
cdk_demo_construct-0.0.186.dist-info/RECORD
