Metadata-Version: 2.1
Name: cdk-demo-construct
Version: 0.0.186
Summary: A sample L3 CDK project
Home-page: https://github.com/neilkuan/cdk-demo-construct.git
Author: Neil Kuan<guan840912@gmail.com>
License: Apache-2.0
Project-URL: Source, https://github.com/neilkuan/cdk-demo-construct.git
Platform: UNKNOWN
Classifier: Intended Audience :: Developers
Classifier: Operating System :: OS Independent
Classifier: Programming Language :: JavaScript
Classifier: Programming Language :: Python :: 3 :: Only
Classifier: Programming Language :: Python :: 3.7
Classifier: Programming Language :: Python :: 3.8
Classifier: Programming Language :: Python :: 3.9
Classifier: Programming Language :: Python :: 3.10
Classifier: Typing :: Typed
Classifier: Development Status :: 5 - Production/Stable
Classifier: License :: OSI Approved
Requires-Python: ~=3.7
License-File: LICENSE
Requires-Dist: aws-cdk.aws-cloudwatch-actions (<2.0.0,>=1.139.0)
Requires-Dist: aws-cdk.aws-cloudwatch (<2.0.0,>=1.139.0)
Requires-Dist: aws-cdk.aws-ec2 (<2.0.0,>=1.139.0)
Requires-Dist: aws-cdk.aws-sns (<2.0.0,>=1.139.0)
Requires-Dist: aws-cdk.core (<2.0.0,>=1.139.0)
Requires-Dist: constructs (<4.0.0,>=3.2.27)
Requires-Dist: jsii (<2.0.0,>=1.62.0)
Requires-Dist: publication (>=0.0.3)
